<?xml version="1.0" encoding="UTF-8"?><?xml-stylesheet type='text/xsl' href='_UpgradeReport_Files/UpgradeReport.xslt'?><UpgradeLog>
<Properties><Property Name="Solution" Value="Novin">
</Property><Property Name="Solution File" Value="G:\Novin\Novin.sln">
</Property><Property Name="User Options File" Value="G:\Novin\Novin.suo">
</Property><Property Name="Date" Value="Wednesday, September 11, 2013">
</Property><Property Name="Time" Value="10:57 AM">
</Property></Properties><Event ErrorLevel="0" Project="" Source="Novin.sln" Description="File successfully backed up as G:\Novin\Backup\Novin.sln">
</Event><Event ErrorLevel="0" Project="" Source="Novin.suo" Description="File successfully backed up as G:\Novin\Backup\Novin.suo">
</Event><Event ErrorLevel="4" Project="Jaavid" Source="http://go.microsoft.com/fwlink/?LinkId=159919" Description="Warning: this project requires Crystal Reports, which is no longer included with Visual Studio. Please click here for more information.">
</Event><Event ErrorLevel="0" Project="Jaavid" Source="Novin\Jaavid.csproj" Description="Project file successfully backed up as G:\Novin\Backup\Novin\Jaavid.csproj">
</Event><Event ErrorLevel="0" Project="Jaavid" Source="Novin\Jaavid.csproj.user" Description="Project user file successfully backed up as G:\Novin\Backup\Novin\Jaavid.csproj.user">
</Event><Event ErrorLevel="0" Project="Jaavid" Source="Novin\cls_accDoc.cs" Description="File successfully backed up as G:\Novin\Backup\Novin\cls_accDoc.cs">
</Event><Event ErrorLevel="0" Project="Jaavid" Source="Novin\cls_cheques.cs" Description="File successfully backed up as G:\Novin\Backup\Novin\cls_cheques.cs">
</Event><Event ErrorLevel="0" Project="Jaavid" Source="Novin\cls_inputBox.cs" Description="File successfully backed up as G:\Novin\Backup\Novin\cls_inputBox.cs">
</Event><Event ErrorLevel="0" Project="Jaavid" Source="Novin\cls_invoices.cs" Description="File successfully backed up as G:\Novin\Backup\Novin\cls_invoices.cs">
</Event><Event ErrorLevel="0" Project="Jaavid" Source="Novin\cls_moeens.cs" Description="File successfully backed up as G:\Novin\Backup\Novin\cls_moeens.cs">
</Event><Event ErrorLevel="0" Project="Jaavid" Source="Novin\cls_msgBox.cs" Description="File successfully backed up as G:\Novin\Backup\Novin\cls_msgBox.cs">
</Event><Event ErrorLevel="0" Project="Jaavid" Source="Novin\cls_pensionForms.cs" Description="File successfully backed up as G:\Novin\Backup\Novin\cls_pensionForms.cs">
</Event><Event ErrorLevel="0" Project="Jaavid" Source="Novin\cls_storing.cs" Description="File successfully backed up as G:\Novin\Backup\Novin\cls_storing.cs">
</Event><Event ErrorLevel="0" Project="Jaavid" Source="Novin\cls_users.cs" Description="File successfully backed up as G:\Novin\Backup\Novin\cls_users.cs">
</Event><Event ErrorLevel="0" Project="Jaavid" Source="Novin\cls_visitors.cs" Description="File successfully backed up as G:\Novin\Backup\Novin\cls_visitors.cs">
</Event><Event ErrorLevel="0" Project="Jaavid" Source="Novin\ds_pensionForms.cs" Description="File successfully backed up as G:\Novin\Backup\Novin\ds_pensionForms.cs">
</Event><Event ErrorLevel="0" Project="Jaavid" Source="Novin\ds_pensionForms.Designer.cs" Description="File successfully backed up as G:\Novin\Backup\Novin\ds_pensionForms.Designer.cs">
</Event><Event ErrorLevel="0" Project="Jaavid" Source="Novin\frm_accountingChapters.cs" Description="File successfully backed up as G:\Novin\Backup\Novin\frm_accountingChapters.cs">
</Event><Event ErrorLevel="0" Project="Jaavid" Source="Novin\frm_accountingChapters.Designer.cs" Description="File successfully backed up as G:\Novin\Backup\Novin\frm_accountingChapters.Designer.cs">
</Event><Event ErrorLevel="0" Project="Jaavid" Source="Novin\frm_backupAndRestore.cs" Description="File successfully backed up as G:\Novin\Backup\Novin\frm_backupAndRestore.cs">
</Event><Event ErrorLevel="0" Project="Jaavid" Source="Novin\frm_backupAndRestore.Designer.cs" Description="File successfully backed up as G:\Novin\Backup\Novin\frm_backupAndRestore.Designer.cs">
</Event><Event ErrorLevel="0" Project="Jaavid" Source="Novin\frm_objectsUnits.cs" Description="File successfully backed up as G:\Novin\Backup\Novin\frm_objectsUnits.cs">
</Event><Event ErrorLevel="0" Project="Jaavid" Source="Novin\frm_objectsUnits.Designer.cs" Description="File successfully backed up as G:\Novin\Backup\Novin\frm_objectsUnits.Designer.cs">
</Event><Event ErrorLevel="0" Project="Jaavid" Source="Novin\frm_soldObjectExplorer.cs" Description="File successfully backed up as G:\Novin\Backup\Novin\frm_soldObjectExplorer.cs">
</Event><Event ErrorLevel="0" Project="Jaavid" Source="Novin\frm_soldObjectExplorer.designer.cs" Description="File successfully backed up as G:\Novin\Backup\Novin\frm_soldObjectExplorer.designer.cs">
</Event><Event ErrorLevel="0" Project="Jaavid" Source="Novin\rpt_indCreList.cs" Description="File successfully backed up as G:\Novin\Backup\Novin\rpt_indCreList.cs">
</Event><Event ErrorLevel="0" Project="Jaavid" Source="Novin\rpt_pensionForm.cs" Description="File successfully backed up as G:\Novin\Backup\Novin\rpt_pensionForm.cs">
</Event><Event ErrorLevel="0" Project="Jaavid" Source="Novin\rpt_profLoss.cs" Description="File successfully backed up as G:\Novin\Backup\Novin\rpt_profLoss.cs">
</Event><Event ErrorLevel="0" Project="Jaavid" Source="Novin\ds_chqs.Designer.cs" Description="File successfully backed up as G:\Novin\Backup\Novin\ds_chqs.Designer.cs">
</Event><Event ErrorLevel="0" Project="Jaavid" Source="Novin\ds_finActs.Designer.cs" Description="File successfully backed up as G:\Novin\Backup\Novin\ds_finActs.Designer.cs">
</Event><Event ErrorLevel="0" Project="Jaavid" Source="Novin\ds_jurnal.Designer.cs" Description="File successfully backed up as G:\Novin\Backup\Novin\ds_jurnal.Designer.cs">
</Event><Event ErrorLevel="0" Project="Jaavid" Source="Novin\ds_objectGrouping.cs" Description="File successfully backed up as G:\Novin\Backup\Novin\ds_objectGrouping.cs">
</Event><Event ErrorLevel="0" Project="Jaavid" Source="Novin\ds_objectLessSell.Designer.cs" Description="File successfully backed up as G:\Novin\Backup\Novin\ds_objectLessSell.Designer.cs">
</Event><Event ErrorLevel="0" Project="Jaavid" Source="Novin\ds_users.Designer.cs" Description="File successfully backed up as G:\Novin\Backup\Novin\ds_users.Designer.cs">
</Event><Event ErrorLevel="0" Project="Jaavid" Source="Novin\ds_visitors.Designer.cs" Description="File successfully backed up as G:\Novin\Backup\Novin\ds_visitors.Designer.cs">
</Event><Event ErrorLevel="0" Project="Jaavid" Source="Novin\frm_accDocExplorer.cs" Description="File successfully backed up as G:\Novin\Backup\Novin\frm_accDocExplorer.cs">
</Event><Event ErrorLevel="0" Project="Jaavid" Source="Novin\frm_accDocExplorer.designer.cs" Description="File successfully backed up as G:\Novin\Backup\Novin\frm_accDocExplorer.designer.cs">
</Event><Event ErrorLevel="0" Project="Jaavid" Source="Novin\frm_chequesExplorer.cs" Description="File successfully backed up as G:\Novin\Backup\Novin\frm_chequesExplorer.cs">
</Event><Event ErrorLevel="0" Project="Jaavid" Source="Novin\frm_chequesExplorer.Designer.cs" Description="File successfully backed up as G:\Novin\Backup\Novin\frm_chequesExplorer.Designer.cs">
</Event><Event ErrorLevel="0" Project="Jaavid" Source="Novin\frm_finActions.cs" Description="File successfully backed up as G:\Novin\Backup\Novin\frm_finActions.cs">
</Event><Event ErrorLevel="0" Project="Jaavid" Source="Novin\frm_finActions.Designer.cs" Description="File successfully backed up as G:\Novin\Backup\Novin\frm_finActions.Designer.cs">
</Event><Event ErrorLevel="0" Project="Jaavid" Source="Novin\frm_logOn.cs" Description="File successfully backed up as G:\Novin\Backup\Novin\frm_logOn.cs">
</Event><Event ErrorLevel="0" Project="Jaavid" Source="Novin\frm_logOn.Designer.cs" Description="File successfully backed up as G:\Novin\Backup\Novin\frm_logOn.Designer.cs">
</Event><Event ErrorLevel="0" Project="Jaavid" Source="Novin\frm_objectEntityReport.cs" Description="File successfully backed up as G:\Novin\Backup\Novin\frm_objectEntityReport.cs">
</Event><Event ErrorLevel="0" Project="Jaavid" Source="Novin\frm_objectEntityReport.Designer.cs" Description="File successfully backed up as G:\Novin\Backup\Novin\frm_objectEntityReport.Designer.cs">
</Event><Event ErrorLevel="0" Project="Jaavid" Source="Novin\frm_pensionForm.cs" Description="File successfully backed up as G:\Novin\Backup\Novin\frm_pensionForm.cs">
</Event><Event ErrorLevel="0" Project="Jaavid" Source="Novin\frm_pensionForm.Designer.cs" Description="File successfully backed up as G:\Novin\Backup\Novin\frm_pensionForm.Designer.cs">
</Event><Event ErrorLevel="0" Project="Jaavid" Source="Novin\frm_setPassword.cs" Description="File successfully backed up as G:\Novin\Backup\Novin\frm_setPassword.cs">
</Event><Event ErrorLevel="0" Project="Jaavid" Source="Novin\frm_setPassword.Designer.cs" Description="File successfully backed up as G:\Novin\Backup\Novin\frm_setPassword.Designer.cs">
</Event><Event ErrorLevel="0" Project="Jaavid" Source="Novin\frm_personExplorer.cs" Description="File successfully backed up as G:\Novin\Backup\Novin\frm_personExplorer.cs">
</Event><Event ErrorLevel="0" Project="Jaavid" Source="Novin\frm_personExplorer.Designer.cs" Description="File successfully backed up as G:\Novin\Backup\Novin\frm_personExplorer.Designer.cs">
</Event><Event ErrorLevel="0" Project="Jaavid" Source="Novin\frm_preferences.cs" Description="File successfully backed up as G:\Novin\Backup\Novin\frm_preferences.cs">
</Event><Event ErrorLevel="0" Project="Jaavid" Source="Novin\frm_preferences.Designer.cs" Description="File successfully backed up as G:\Novin\Backup\Novin\frm_preferences.Designer.cs">
</Event><Event ErrorLevel="0" Project="Jaavid" Source="Novin\frm_visitors.cs" Description="File successfully backed up as G:\Novin\Backup\Novin\frm_visitors.cs">
</Event><Event ErrorLevel="0" Project="Jaavid" Source="Novin\frm_visitors.Designer.cs" Description="File successfully backed up as G:\Novin\Backup\Novin\frm_visitors.Designer.cs">
</Event><Event ErrorLevel="0" Project="Jaavid" Source="Novin\rpt_accDoc.cs" Description="File successfully backed up as G:\Novin\Backup\Novin\rpt_accDoc.cs">
</Event><Event ErrorLevel="0" Project="Jaavid" Source="Novin\rpt_chequesList.cs" Description="File successfully backed up as G:\Novin\Backup\Novin\rpt_chequesList.cs">
</Event><Event ErrorLevel="0" Project="Jaavid" Source="Novin\rpt_dualBalance1.cs" Description="File successfully backed up as G:\Novin\Backup\Novin\rpt_dualBalance1.cs">
</Event><Event ErrorLevel="0" Project="Jaavid" Source="Novin\ds_accounting.Designer.cs" Description="File successfully backed up as G:\Novin\Backup\Novin\ds_accounting.Designer.cs">
</Event><Event ErrorLevel="0" Project="Jaavid" Source="Novin\ds_experBalance.Designer.cs" Description="File successfully backed up as G:\Novin\Backup\Novin\ds_experBalance.Designer.cs">
</Event><Event ErrorLevel="0" Project="Jaavid" Source="Novin\ds_sellInvoices.cs" Description="File successfully backed up as G:\Novin\Backup\Novin\ds_sellInvoices.cs">
</Event><Event ErrorLevel="0" Project="Jaavid" Source="Novin\ds_stores.Designer.cs" Description="File successfully backed up as G:\Novin\Backup\Novin\ds_stores.Designer.cs">
</Event><Event ErrorLevel="0" Project="Jaavid" Source="Novin\ds_wastedInvoices.cs" Description="File successfully backed up as G:\Novin\Backup\Novin\ds_wastedInvoices.cs">
</Event><Event ErrorLevel="0" Project="Jaavid" Source="Novin\ds_wastedInvoices.Designer.cs" Description="File successfully backed up as G:\Novin\Backup\Novin\ds_wastedInvoices.Designer.cs">
</Event><Event ErrorLevel="0" Project="Jaavid" Source="Novin\ds_accounts.Designer.cs" Description="File successfully backed up as G:\Novin\Backup\Novin\ds_accounts.Designer.cs">
</Event><Event ErrorLevel="0" Project="Jaavid" Source="Novin\ds_buyInvoices.cs" Description="File successfully backed up as G:\Novin\Backup\Novin\ds_buyInvoices.cs">
</Event><Event ErrorLevel="0" Project="Jaavid" Source="Novin\ds_buyInvoices.Designer.cs" Description="File successfully backed up as G:\Novin\Backup\Novin\ds_buyInvoices.Designer.cs">
</Event><Event ErrorLevel="0" Project="Jaavid" Source="Novin\ds_objectGrouping.Designer.cs" Description="File successfully backed up as G:\Novin\Backup\Novin\ds_objectGrouping.Designer.cs">
</Event><Event ErrorLevel="0" Project="Jaavid" Source="Novin\ds_persons.Designer.cs" Description="File successfully backed up as G:\Novin\Backup\Novin\ds_persons.Designer.cs">
</Event><Event ErrorLevel="0" Project="Jaavid" Source="Novin\ds_sellInvoices1.Designer.cs" Description="File successfully backed up as G:\Novin\Backup\Novin\ds_sellInvoices1.Designer.cs">
</Event><Event ErrorLevel="0" Project="Jaavid" Source="Novin\ds_viewAccounts.cs" Description="File successfully backed up as G:\Novin\Backup\Novin\ds_viewAccounts.cs">
</Event><Event ErrorLevel="0" Project="Jaavid" Source="Novin\ds_viewAccounts.Designer.cs" Description="File successfully backed up as G:\Novin\Backup\Novin\ds_viewAccounts.Designer.cs">
</Event><Event ErrorLevel="0" Project="Jaavid" Source="Novin\ds_viewCheques.Designer.cs" Description="File successfully backed up as G:\Novin\Backup\Novin\ds_viewCheques.Designer.cs">
</Event><Event ErrorLevel="0" Project="Jaavid" Source="Novin\ds_viewIndebtedCreditor.cs" Description="File successfully backed up as G:\Novin\Backup\Novin\ds_viewIndebtedCreditor.cs">
</Event><Event ErrorLevel="0" Project="Jaavid" Source="Novin\ds_viewIndebtedCreditor.Designer.cs" Description="File successfully backed up as G:\Novin\Backup\Novin\ds_viewIndebtedCreditor.Designer.cs">
</Event><Event ErrorLevel="0" Project="Jaavid" Source="Novin\frm_accountsPrimaryMoney.cs" Description="File successfully backed up as G:\Novin\Backup\Novin\frm_accountsPrimaryMoney.cs">
</Event><Event ErrorLevel="0" Project="Jaavid" Source="Novin\frm_accountsPrimaryMoney.Designer.cs" Description="File successfully backed up as G:\Novin\Backup\Novin\frm_accountsPrimaryMoney.Designer.cs">
</Event><Event ErrorLevel="0" Project="Jaavid" Source="Novin\frm_books.cs" Description="File successfully backed up as G:\Novin\Backup\Novin\frm_books.cs">
</Event><Event ErrorLevel="0" Project="Jaavid" Source="Novin\frm_books.Designer.cs" Description="File successfully backed up as G:\Novin\Backup\Novin\frm_books.Designer.cs">
</Event><Event ErrorLevel="0" Project="Jaavid" Source="Novin\frm_experBalance.cs" Description="File successfully backed up as G:\Novin\Backup\Novin\frm_experBalance.cs">
</Event><Event ErrorLevel="0" Project="Jaavid" Source="Novin\frm_experBalance.Designer.cs" Description="File successfully backed up as G:\Novin\Backup\Novin\frm_experBalance.Designer.cs">
</Event><Event ErrorLevel="0" Project="Jaavid" Source="Novin\frm_FATHER.cs" Description="File successfully backed up as G:\Novin\Backup\Novin\frm_FATHER.cs">
</Event><Event ErrorLevel="0" Project="Jaavid" Source="Novin\frm_FATHER.Designer.cs" Description="File successfully backed up as G:\Novin\Backup\Novin\frm_FATHER.Designer.cs">
</Event><Event ErrorLevel="0" Project="Jaavid" Source="Novin\frm_findRecords.cs" Description="File successfully backed up as G:\Novin\Backup\Novin\frm_findRecords.cs">
</Event><Event ErrorLevel="0" Project="Jaavid" Source="Novin\frm_findRecords.designer.cs" Description="File successfully backed up as G:\Novin\Backup\Novin\frm_findRecords.designer.cs">
</Event><Event ErrorLevel="0" Project="Jaavid" Source="Novin\frm_invoiceExplorer.cs" Description="File successfully backed up as G:\Novin\Backup\Novin\frm_invoiceExplorer.cs">
</Event><Event ErrorLevel="0" Project="Jaavid" Source="Novin\frm_invoiceExplorer.Designer.cs" Description="File successfully backed up as G:\Novin\Backup\Novin\frm_invoiceExplorer.Designer.cs">
</Event><Event ErrorLevel="0" Project="Jaavid" Source="Novin\frm_invoicesBuy.cs" Description="File successfully backed up as G:\Novin\Backup\Novin\frm_invoicesBuy.cs">
</Event><Event ErrorLevel="0" Project="Jaavid" Source="Novin\frm_invoicesBuy.Designer.cs" Description="File successfully backed up as G:\Novin\Backup\Novin\frm_invoicesBuy.Designer.cs">
</Event><Event ErrorLevel="0" Project="Jaavid" Source="Novin\frm_invoicesSell.cs" Description="File successfully backed up as G:\Novin\Backup\Novin\frm_invoicesSell.cs">
</Event><Event ErrorLevel="0" Project="Jaavid" Source="Novin\frm_invoicesSell.Designer.cs" Description="File successfully backed up as G:\Novin\Backup\Novin\frm_invoicesSell.Designer.cs">
</Event><Event ErrorLevel="0" Project="Jaavid" Source="Novin\frm_invoicesWasted.cs" Description="File successfully backed up as G:\Novin\Backup\Novin\frm_invoicesWasted.cs">
</Event><Event ErrorLevel="0" Project="Jaavid" Source="Novin\frm_invoicesWasted.Designer.cs" Description="File successfully backed up as G:\Novin\Backup\Novin\frm_invoicesWasted.Designer.cs">
</Event><Event ErrorLevel="0" Project="Jaavid" Source="Novin\frm_issuseAccDoc.cs" Description="File successfully backed up as G:\Novin\Backup\Novin\frm_issuseAccDoc.cs">
</Event><Event ErrorLevel="0" Project="Jaavid" Source="Novin\frm_issuseAccDoc.Designer.cs" Description="File successfully backed up as G:\Novin\Backup\Novin\frm_issuseAccDoc.Designer.cs">
</Event><Event ErrorLevel="0" Project="Jaavid" Source="Novin\frm_itemSelection.cs" Description="File successfully backed up as G:\Novin\Backup\Novin\frm_itemSelection.cs">
</Event><Event ErrorLevel="0" Project="Jaavid" Source="Novin\frm_itemSelection.Designer.cs" Description="File successfully backed up as G:\Novin\Backup\Novin\frm_itemSelection.Designer.cs">
</Event><Event ErrorLevel="0" Project="Jaavid" Source="Novin\frm_modify.cs" Description="File successfully backed up as G:\Novin\Backup\Novin\frm_modify.cs">
</Event><Event ErrorLevel="0" Project="Jaavid" Source="Novin\frm_modify.Designer.cs" Description="File successfully backed up as G:\Novin\Backup\Novin\frm_modify.Designer.cs">
</Event><Event ErrorLevel="0" Project="Jaavid" Source="Novin\frm_msgBox.cs" Description="File successfully backed up as G:\Novin\Backup\Novin\frm_msgBox.cs">
</Event><Event ErrorLevel="0" Project="Jaavid" Source="Novin\frm_msgBox.Designer.cs" Description="File successfully backed up as G:\Novin\Backup\Novin\frm_msgBox.Designer.cs">
</Event><Event ErrorLevel="0" Project="Jaavid" Source="Novin\cls_numberConvertor.cs" Description="File successfully backed up as G:\Novin\Backup\Novin\cls_numberConvertor.cs">
</Event><Event ErrorLevel="0" Project="Jaavid" Source="Novin\frm_accounts.cs" Description="File successfully backed up as G:\Novin\Backup\Novin\frm_accounts.cs">
</Event><Event ErrorLevel="0" Project="Jaavid" Source="Novin\frm_accounts.designer.cs" Description="File successfully backed up as G:\Novin\Backup\Novin\frm_accounts.designer.cs">
</Event><Event ErrorLevel="0" Project="Jaavid" Source="Novin\frm_bank.cs" Description="File successfully backed up as G:\Novin\Backup\Novin\frm_bank.cs">
</Event><Event ErrorLevel="0" Project="Jaavid" Source="Novin\frm_bank.designer.cs" Description="File successfully backed up as G:\Novin\Backup\Novin\frm_bank.designer.cs">
</Event><Event ErrorLevel="0" Project="Jaavid" Source="Novin\frm_cheques.cs" Description="File successfully backed up as G:\Novin\Backup\Novin\frm_cheques.cs">
</Event><Event ErrorLevel="0" Project="Jaavid" Source="Novin\frm_cheques.designer.cs" Description="File successfully backed up as G:\Novin\Backup\Novin\frm_cheques.designer.cs">
</Event><Event ErrorLevel="0" Project="Jaavid" Source="Novin\frm_inputBox.cs" Description="File successfully backed up as G:\Novin\Backup\Novin\frm_inputBox.cs">
</Event><Event ErrorLevel="0" Project="Jaavid" Source="Novin\frm_inputBox.Designer.cs" Description="File successfully backed up as G:\Novin\Backup\Novin\frm_inputBox.Designer.cs">
</Event><Event ErrorLevel="0" Project="Jaavid" Source="Novin\frm_primaryCycleEnd.cs" Description="File successfully backed up as G:\Novin\Backup\Novin\frm_primaryCycleEnd.cs">
</Event><Event ErrorLevel="0" Project="Jaavid" Source="Novin\frm_primaryCycleEnd.Designer.cs" Description="File successfully backed up as G:\Novin\Backup\Novin\frm_primaryCycleEnd.Designer.cs">
</Event><Event ErrorLevel="0" Project="Jaavid" Source="Novin\frm_print.cs" Description="File successfully backed up as G:\Novin\Backup\Novin\frm_print.cs">
</Event><Event ErrorLevel="0" Project="Jaavid" Source="Novin\frm_print.Designer.cs" Description="File successfully backed up as G:\Novin\Backup\Novin\frm_print.Designer.cs">
</Event><Event ErrorLevel="0" Project="Jaavid" Source="Novin\frm_reportPreview.cs" Description="File successfully backed up as G:\Novin\Backup\Novin\frm_reportPreview.cs">
</Event><Event ErrorLevel="0" Project="Jaavid" Source="Novin\frm_reportPreview.Designer.cs" Description="File successfully backed up as G:\Novin\Backup\Novin\frm_reportPreview.Designer.cs">
</Event><Event ErrorLevel="0" Project="Jaavid" Source="Novin\frm_store.cs" Description="File successfully backed up as G:\Novin\Backup\Novin\frm_store.cs">
</Event><Event ErrorLevel="0" Project="Jaavid" Source="Novin\frm_store.designer.cs" Description="File successfully backed up as G:\Novin\Backup\Novin\frm_store.designer.cs">
</Event><Event ErrorLevel="0" Project="Jaavid" Source="Novin\rpt_balance.cs" Description="File successfully backed up as G:\Novin\Backup\Novin\rpt_balance.cs">
</Event><Event ErrorLevel="0" Project="Jaavid" Source="Novin\rpt_invoiceBuy.cs" Description="File successfully backed up as G:\Novin\Backup\Novin\rpt_invoiceBuy.cs">
</Event><Event ErrorLevel="0" Project="Jaavid" Source="Novin\rpt_invoiceSell.cs" Description="File successfully backed up as G:\Novin\Backup\Novin\rpt_invoiceSell.cs">
</Event><Event ErrorLevel="0" Project="Jaavid" Source="Novin\rpt_journal.cs" Description="File successfully backed up as G:\Novin\Backup\Novin\rpt_journal.cs">
</Event><Event ErrorLevel="0" Project="Jaavid" Source="Novin\rpt_ledger.cs" Description="File successfully backed up as G:\Novin\Backup\Novin\rpt_ledger.cs">
</Event><Event ErrorLevel="0" Project="Jaavid" Source="Novin\rpt_objectEntity.cs" Description="File successfully backed up as G:\Novin\Backup\Novin\rpt_objectEntity.cs">
</Event><Event ErrorLevel="0" Project="Jaavid" Source="Novin\rpt_objectWasted.cs" Description="File successfully backed up as G:\Novin\Backup\Novin\rpt_objectWasted.cs">
</Event><Event ErrorLevel="0" Project="Jaavid" Source="Novin\tbl_slaveGroups.cs" Description="File successfully backed up as G:\Novin\Backup\Novin\tbl_slaveGroups.cs">
</Event><Event ErrorLevel="0" Project="Jaavid" Source="Novin\frm_master.cs" Description="File successfully backed up as G:\Novin\Backup\Novin\frm_master.cs">
</Event><Event ErrorLevel="0" Project="Jaavid" Source="Novin\frm_master.Designer.cs" Description="File successfully backed up as G:\Novin\Backup\Novin\frm_master.Designer.cs">
</Event><Event ErrorLevel="0" Project="Jaavid" Source="Novin\frm_objectGrouping.cs" Description="File successfully backed up as G:\Novin\Backup\Novin\frm_objectGrouping.cs">
</Event><Event ErrorLevel="0" Project="Jaavid" Source="Novin\frm_objectGrouping.Designer.cs" Description="File successfully backed up as G:\Novin\Backup\Novin\frm_objectGrouping.Designer.cs">
</Event><Event ErrorLevel="0" Project="Jaavid" Source="Novin\frm_objects.cs" Description="File successfully backed up as G:\Novin\Backup\Novin\frm_objects.cs">
</Event><Event ErrorLevel="0" Project="Jaavid" Source="Novin\frm_objects.Designer.cs" Description="File successfully backed up as G:\Novin\Backup\Novin\frm_objects.Designer.cs">
</Event><Event ErrorLevel="0" Project="Jaavid" Source="Novin\frm_persons.cs" Description="File successfully backed up as G:\Novin\Backup\Novin\frm_persons.cs">
</Event><Event ErrorLevel="0" Project="Jaavid" Source="Novin\frm_persons.designer.cs" Description="File successfully backed up as G:\Novin\Backup\Novin\frm_persons.designer.cs">
</Event><Event ErrorLevel="0" Project="Jaavid" Source="Novin\cls_myDataAccessLayer.cs" Description="File successfully backed up as G:\Novin\Backup\Novin\cls_myDataAccessLayer.cs">
</Event><Event ErrorLevel="0" Project="Jaavid" Source="Novin\Program.cs" Description="File successfully backed up as G:\Novin\Backup\Novin\Program.cs">
</Event><Event ErrorLevel="0" Project="Jaavid" Source="Novin\Properties\AssemblyInfo.cs" Description="File successfully backed up as G:\Novin\Backup\Novin\Properties\AssemblyInfo.cs">
</Event><Event ErrorLevel="0" Project="Jaavid" Source="Novin\Properties\Resources.Designer.cs" Description="File successfully backed up as G:\Novin\Backup\Novin\Properties\Resources.Designer.cs">
</Event><Event ErrorLevel="0" Project="Jaavid" Source="Novin\Properties\Settings.Designer.cs" Description="File successfully backed up as G:\Novin\Backup\Novin\Properties\Settings.Designer.cs">
</Event><Event ErrorLevel="0" Project="Jaavid" Source="Novin\tbl_masterGroups.cs" Description="File successfully backed up as G:\Novin\Backup\Novin\tbl_masterGroups.cs">
</Event><Event ErrorLevel="0" Project="Jaavid" Source="Novin\Properties\Settings.settings" Description="File successfully backed up as G:\Novin\Backup\Novin\Properties\Settings.settings">
</Event><Event ErrorLevel="0" Project="Jaavid" Source="Novin\ds_pensionForms.xsc" Description="File successfully backed up as G:\Novin\Backup\Novin\ds_pensionForms.xsc">
</Event><Event ErrorLevel="0" Project="Jaavid" Source="Novin\ds_pensionForms.xsd" Description="File successfully backed up as G:\Novin\Backup\Novin\ds_pensionForms.xsd">
</Event><Event ErrorLevel="0" Project="Jaavid" Source="Novin\ds_pensionForms.xss" Description="File successfully backed up as G:\Novin\Backup\Novin\ds_pensionForms.xss">
</Event><Event ErrorLevel="0" Project="Jaavid" Source="Novin\Resources\ultimateredma5.jpg" Description="File successfully backed up as G:\Novin\Backup\Novin\Resources\ultimateredma5.jpg">
</Event><Event ErrorLevel="0" Project="Jaavid" Source="Novin\ds_users.xsc" Description="File successfully backed up as G:\Novin\Backup\Novin\ds_users.xsc">
</Event><Event ErrorLevel="0" Project="Jaavid" Source="Novin\ds_users.xsd" Description="File successfully backed up as G:\Novin\Backup\Novin\ds_users.xsd">
</Event><Event ErrorLevel="0" Project="Jaavid" Source="Novin\ds_users.xss" Description="File successfully backed up as G:\Novin\Backup\Novin\ds_users.xss">
</Event><Event ErrorLevel="0" Project="Jaavid" Source="Novin\Resources\monitor2.bmp" Description="File successfully backed up as G:\Novin\Backup\Novin\Resources\monitor2.bmp">
</Event><Event ErrorLevel="0" Project="Jaavid" Source="Novin\ds_accounting.xsc" Description="File successfully backed up as G:\Novin\Backup\Novin\ds_accounting.xsc">
</Event><Event ErrorLevel="0" Project="Jaavid" Source="Novin\ds_accounting.xsd" Description="File successfully backed up as G:\Novin\Backup\Novin\ds_accounting.xsd">
</Event><Event ErrorLevel="0" Project="Jaavid" Source="Novin\ds_accounting.xss" Description="File successfully backed up as G:\Novin\Backup\Novin\ds_accounting.xss">
</Event><Event ErrorLevel="0" Project="Jaavid" Source="Novin\ds_accounts.xsc" Description="File successfully backed up as G:\Novin\Backup\Novin\ds_accounts.xsc">
</Event><Event ErrorLevel="0" Project="Jaavid" Source="Novin\ds_accounts.xsd" Description="File successfully backed up as G:\Novin\Backup\Novin\ds_accounts.xsd">
</Event><Event ErrorLevel="0" Project="Jaavid" Source="Novin\ds_accounts.xss" Description="File successfully backed up as G:\Novin\Backup\Novin\ds_accounts.xss">
</Event><Event ErrorLevel="0" Project="Jaavid" Source="Novin\ds_buyInvoices.xsc" Description="File successfully backed up as G:\Novin\Backup\Novin\ds_buyInvoices.xsc">
</Event><Event ErrorLevel="0" Project="Jaavid" Source="Novin\ds_buyInvoices.xsd" Description="File successfully backed up as G:\Novin\Backup\Novin\ds_buyInvoices.xsd">
</Event><Event ErrorLevel="0" Project="Jaavid" Source="Novin\ds_buyInvoices.xss" Description="File successfully backed up as G:\Novin\Backup\Novin\ds_buyInvoices.xss">
</Event><Event ErrorLevel="0" Project="Jaavid" Source="Novin\ds_chqs.xsc" Description="File successfully backed up as G:\Novin\Backup\Novin\ds_chqs.xsc">
</Event><Event ErrorLevel="0" Project="Jaavid" Source="Novin\ds_chqs.xsd" Description="File successfully backed up as G:\Novin\Backup\Novin\ds_chqs.xsd">
</Event><Event ErrorLevel="0" Project="Jaavid" Source="Novin\ds_chqs.xss" Description="File successfully backed up as G:\Novin\Backup\Novin\ds_chqs.xss">
</Event><Event ErrorLevel="0" Project="Jaavid" Source="Novin\ds_experBalance.xsc" Description="File successfully backed up as G:\Novin\Backup\Novin\ds_experBalance.xsc">
</Event><Event ErrorLevel="0" Project="Jaavid" Source="Novin\ds_experBalance.xsd" Description="File successfully backed up as G:\Novin\Backup\Novin\ds_experBalance.xsd">
</Event><Event ErrorLevel="0" Project="Jaavid" Source="Novin\ds_experBalance.xss" Description="File successfully backed up as G:\Novin\Backup\Novin\ds_experBalance.xss">
</Event><Event ErrorLevel="0" Project="Jaavid" Source="Novin\ds_finActs.xsc" Description="File successfully backed up as G:\Novin\Backup\Novin\ds_finActs.xsc">
</Event><Event ErrorLevel="0" Project="Jaavid" Source="Novin\ds_finActs.xsd" Description="File successfully backed up as G:\Novin\Backup\Novin\ds_finActs.xsd">
</Event><Event ErrorLevel="0" Project="Jaavid" Source="Novin\ds_finActs.xss" Description="File successfully backed up as G:\Novin\Backup\Novin\ds_finActs.xss">
</Event><Event ErrorLevel="0" Project="Jaavid" Source="Novin\ds_jurnal.xsc" Description="File successfully backed up as G:\Novin\Backup\Novin\ds_jurnal.xsc">
</Event><Event ErrorLevel="0" Project="Jaavid" Source="Novin\ds_jurnal.xsd" Description="File successfully backed up as G:\Novin\Backup\Novin\ds_jurnal.xsd">
</Event><Event ErrorLevel="0" Project="Jaavid" Source="Novin\ds_jurnal.xss" Description="File successfully backed up as G:\Novin\Backup\Novin\ds_jurnal.xss">
</Event><Event ErrorLevel="0" Project="Jaavid" Source="Novin\ds_objectLessSell.xsc" Description="File successfully backed up as G:\Novin\Backup\Novin\ds_objectLessSell.xsc">
</Event><Event ErrorLevel="0" Project="Jaavid" Source="Novin\ds_objectLessSell.xsd" Description="File successfully backed up as G:\Novin\Backup\Novin\ds_objectLessSell.xsd">
</Event><Event ErrorLevel="0" Project="Jaavid" Source="Novin\ds_objectLessSell.xss" Description="File successfully backed up as G:\Novin\Backup\Novin\ds_objectLessSell.xss">
</Event><Event ErrorLevel="0" Project="Jaavid" Source="Novin\ds_persons.xsc" Description="File successfully backed up as G:\Novin\Backup\Novin\ds_persons.xsc">
</Event><Event ErrorLevel="0" Project="Jaavid" Source="Novin\ds_persons.xsd" Description="File successfully backed up as G:\Novin\Backup\Novin\ds_persons.xsd">
</Event><Event ErrorLevel="0" Project="Jaavid" Source="Novin\ds_persons.xss" Description="File successfully backed up as G:\Novin\Backup\Novin\ds_persons.xss">
</Event><Event ErrorLevel="0" Project="Jaavid" Source="Novin\ds_sellInvoices.xsc" Description="File successfully backed up as G:\Novin\Backup\Novin\ds_sellInvoices.xsc">
</Event><Event ErrorLevel="0" Project="Jaavid" Source="Novin\ds_sellInvoices.xsd" Description="File successfully backed up as G:\Novin\Backup\Novin\ds_sellInvoices.xsd">
</Event><Event ErrorLevel="0" Project="Jaavid" Source="Novin\ds_sellInvoices.xss" Description="File successfully backed up as G:\Novin\Backup\Novin\ds_sellInvoices.xss">
</Event><Event ErrorLevel="0" Project="Jaavid" Source="Novin\ds_stores.xsc" Description="File successfully backed up as G:\Novin\Backup\Novin\ds_stores.xsc">
</Event><Event ErrorLevel="0" Project="Jaavid" Source="Novin\ds_stores.xsd" Description="File successfully backed up as G:\Novin\Backup\Novin\ds_stores.xsd">
</Event><Event ErrorLevel="0" Project="Jaavid" Source="Novin\ds_stores.xss" Description="File successfully backed up as G:\Novin\Backup\Novin\ds_stores.xss">
</Event><Event ErrorLevel="0" Project="Jaavid" Source="Novin\ds_viewAccounts.xsc" Description="File successfully backed up as G:\Novin\Backup\Novin\ds_viewAccounts.xsc">
</Event><Event ErrorLevel="0" Project="Jaavid" Source="Novin\ds_viewAccounts.xsd" Description="File successfully backed up as G:\Novin\Backup\Novin\ds_viewAccounts.xsd">
</Event><Event ErrorLevel="0" Project="Jaavid" Source="Novin\ds_viewAccounts.xss" Description="File successfully backed up as G:\Novin\Backup\Novin\ds_viewAccounts.xss">
</Event><Event ErrorLevel="0" Project="Jaavid" Source="Novin\ds_viewCheques.xsc" Description="File successfully backed up as G:\Novin\Backup\Novin\ds_viewCheques.xsc">
</Event><Event ErrorLevel="0" Project="Jaavid" Source="Novin\ds_viewCheques.xsd" Description="File successfully backed up as G:\Novin\Backup\Novin\ds_viewCheques.xsd">
</Event><Event ErrorLevel="0" Project="Jaavid" Source="Novin\ds_viewCheques.xss" Description="File successfully backed up as G:\Novin\Backup\Novin\ds_viewCheques.xss">
</Event><Event ErrorLevel="0" Project="Jaavid" Source="Novin\ds_viewIndebtedCreditor.xsc" Description="File successfully backed up as G:\Novin\Backup\Novin\ds_viewIndebtedCreditor.xsc">
</Event><Event ErrorLevel="0" Project="Jaavid" Source="Novin\ds_viewIndebtedCreditor.xsd" Description="File successfully backed up as G:\Novin\Backup\Novin\ds_viewIndebtedCreditor.xsd">
</Event><Event ErrorLevel="0" Project="Jaavid" Source="Novin\ds_viewIndebtedCreditor.xss" Description="File successfully backed up as G:\Novin\Backup\Novin\ds_viewIndebtedCreditor.xss">
</Event><Event ErrorLevel="0" Project="Jaavid" Source="Novin\ds_visitors.xsc" Description="File successfully backed up as G:\Novin\Backup\Novin\ds_visitors.xsc">
</Event><Event ErrorLevel="0" Project="Jaavid" Source="Novin\ds_visitors.xsd" Description="File successfully backed up as G:\Novin\Backup\Novin\ds_visitors.xsd">
</Event><Event ErrorLevel="0" Project="Jaavid" Source="Novin\ds_visitors.xss" Description="File successfully backed up as G:\Novin\Backup\Novin\ds_visitors.xss">
</Event><Event ErrorLevel="0" Project="Jaavid" Source="Novin\ds_wastedInvoices.xsc" Description="File successfully backed up as G:\Novin\Backup\Novin\ds_wastedInvoices.xsc">
</Event><Event ErrorLevel="0" Project="Jaavid" Source="Novin\ds_wastedInvoices.xsd" Description="File successfully backed up as G:\Novin\Backup\Novin\ds_wastedInvoices.xsd">
</Event><Event ErrorLevel="0" Project="Jaavid" Source="Novin\ds_wastedInvoices.xss" Description="File successfully backed up as G:\Novin\Backup\Novin\ds_wastedInvoices.xss">
</Event><Event ErrorLevel="0" Project="Jaavid" Source="Novin\Resources\Wallpaper -(1).jpg" Description="File successfully backed up as G:\Novin\Backup\Novin\Resources\Wallpaper -(1).jpg">
</Event><Event ErrorLevel="0" Project="Jaavid" Source="Novin\ds_objectGrouping.xsc" Description="File successfully backed up as G:\Novin\Backup\Novin\ds_objectGrouping.xsc">
</Event><Event ErrorLevel="0" Project="Jaavid" Source="Novin\ds_objectGrouping.xsd" Description="File successfully backed up as G:\Novin\Backup\Novin\ds_objectGrouping.xsd">
</Event><Event ErrorLevel="0" Project="Jaavid" Source="Novin\ds_objectGrouping.xss" Description="File successfully backed up as G:\Novin\Backup\Novin\ds_objectGrouping.xss">
</Event><Event ErrorLevel="0" Project="Jaavid" Source="Novin\Resources\notice-note.png" Description="File successfully backed up as G:\Novin\Backup\Novin\Resources\notice-note.png">
</Event><Event ErrorLevel="0" Project="Jaavid" Source="Novin\Resources\notice-info.png" Description="File successfully backed up as G:\Novin\Backup\Novin\Resources\notice-info.png">
</Event><Event ErrorLevel="0" Project="Jaavid" Source="Novin\Resources\checkin.png" Description="File successfully backed up as G:\Novin\Backup\Novin\Resources\checkin.png">
</Event><Event ErrorLevel="0" Project="Jaavid" Source="Novin\app.config" Description="File successfully backed up as G:\Novin\Backup\Novin\app.config">
</Event><Event ErrorLevel="0" Project="Jaavid" Source="Novin\Resources\Wallpaper -(8).jpg" Description="File successfully backed up as G:\Novin\Backup\Novin\Resources\Wallpaper -(8).jpg">
</Event><Event ErrorLevel="0" Project="Jaavid" Source="Novin\Resources\mainHead.jpg" Description="File successfully backed up as G:\Novin\Backup\Novin\Resources\mainHead.jpg">
</Event><Event ErrorLevel="0" Project="Jaavid" Source="Novin\Resources\unique_wallpapers_from_europe (6).jpg" Description="File successfully backed up as G:\Novin\Backup\Novin\Resources\unique_wallpapers_from_europe (6).jpg">
</Event><Event ErrorLevel="0" Project="Jaavid" Source="Novin\Resources\forms_template.jpg" Description="File successfully backed up as G:\Novin\Backup\Novin\Resources\forms_template.jpg">
</Event><Event ErrorLevel="0" Project="Jaavid" Source="Novin\novinDB.mdf" Description="File successfully backed up as G:\Novin\Backup\Novin\novinDB.mdf">
</Event><Event ErrorLevel="0" Project="Jaavid" Source="Novin\novinDB_log.ldf" Description="File successfully backed up as G:\Novin\Backup\Novin\novinDB_log.ldf">
</Event><Event ErrorLevel="0" Project="Jaavid" Source="Novin\frm_accountingChapters.resx" Description="File successfully backed up as G:\Novin\Backup\Novin\frm_accountingChapters.resx">
</Event><Event ErrorLevel="0" Project="Jaavid" Source="Novin\frm_backupAndRestore.resx" Description="File successfully backed up as G:\Novin\Backup\Novin\frm_backupAndRestore.resx">
</Event><Event ErrorLevel="0" Project="Jaavid" Source="Novin\frm_objectsUnits.resx" Description="File successfully backed up as G:\Novin\Backup\Novin\frm_objectsUnits.resx">
</Event><Event ErrorLevel="0" Project="Jaavid" Source="Novin\frm_soldObjectExplorer.resx" Description="File successfully backed up as G:\Novin\Backup\Novin\frm_soldObjectExplorer.resx">
</Event><Event ErrorLevel="0" Project="Jaavid" Source="Novin\rpt_indCreList.rpt" Description="File successfully backed up as G:\Novin\Backup\Novin\rpt_indCreList.rpt">
</Event><Event ErrorLevel="0" Project="Jaavid" Source="Novin\rpt_pensionForm.rpt" Description="File successfully backed up as G:\Novin\Backup\Novin\rpt_pensionForm.rpt">
</Event><Event ErrorLevel="0" Project="Jaavid" Source="Novin\rpt_profLoss.rpt" Description="File successfully backed up as G:\Novin\Backup\Novin\rpt_profLoss.rpt">
</Event><Event ErrorLevel="0" Project="Jaavid" Source="Novin\frm_accDocExplorer.resx" Description="File successfully backed up as G:\Novin\Backup\Novin\frm_accDocExplorer.resx">
</Event><Event ErrorLevel="0" Project="Jaavid" Source="Novin\frm_chequesExplorer.resx" Description="File successfully backed up as G:\Novin\Backup\Novin\frm_chequesExplorer.resx">
</Event><Event ErrorLevel="0" Project="Jaavid" Source="Novin\frm_finActions.resx" Description="File successfully backed up as G:\Novin\Backup\Novin\frm_finActions.resx">
</Event><Event ErrorLevel="0" Project="Jaavid" Source="Novin\frm_logOn.resx" Description="File successfully backed up as G:\Novin\Backup\Novin\frm_logOn.resx">
</Event><Event ErrorLevel="0" Project="Jaavid" Source="Novin\frm_objectEntityReport.resx" Description="File successfully backed up as G:\Novin\Backup\Novin\frm_objectEntityReport.resx">
</Event><Event ErrorLevel="0" Project="Jaavid" Source="Novin\frm_pensionForm.resx" Description="File successfully backed up as G:\Novin\Backup\Novin\frm_pensionForm.resx">
</Event><Event ErrorLevel="0" Project="Jaavid" Source="Novin\frm_personExplorer.resx" Description="File successfully backed up as G:\Novin\Backup\Novin\frm_personExplorer.resx">
</Event><Event ErrorLevel="0" Project="Jaavid" Source="Novin\frm_preferences.resx" Description="File successfully backed up as G:\Novin\Backup\Novin\frm_preferences.resx">
</Event><Event ErrorLevel="0" Project="Jaavid" Source="Novin\frm_setPassword.resx" Description="File successfully backed up as G:\Novin\Backup\Novin\frm_setPassword.resx">
</Event><Event ErrorLevel="0" Project="Jaavid" Source="Novin\frm_visitors.resx" Description="File successfully backed up as G:\Novin\Backup\Novin\frm_visitors.resx">
</Event><Event ErrorLevel="0" Project="Jaavid" Source="Novin\rpt_accDoc.rpt" Description="File successfully backed up as G:\Novin\Backup\Novin\rpt_accDoc.rpt">
</Event><Event ErrorLevel="0" Project="Jaavid" Source="Novin\rpt_chequesList.rpt" Description="File successfully backed up as G:\Novin\Backup\Novin\rpt_chequesList.rpt">
</Event><Event ErrorLevel="0" Project="Jaavid" Source="Novin\rpt_dualBalance.rpt" Description="File successfully backed up as G:\Novin\Backup\Novin\rpt_dualBalance.rpt">
</Event><Event ErrorLevel="0" Project="Jaavid" Source="Novin\frm_accounts.resx" Description="File successfully backed up as G:\Novin\Backup\Novin\frm_accounts.resx">
</Event><Event ErrorLevel="0" Project="Jaavid" Source="Novin\frm_accountsPrimaryMoney.resx" Description="File successfully backed up as G:\Novin\Backup\Novin\frm_accountsPrimaryMoney.resx">
</Event><Event ErrorLevel="0" Project="Jaavid" Source="Novin\frm_bank.resx" Description="File successfully backed up as G:\Novin\Backup\Novin\frm_bank.resx">
</Event><Event ErrorLevel="0" Project="Jaavid" Source="Novin\frm_books.resx" Description="File successfully backed up as G:\Novin\Backup\Novin\frm_books.resx">
</Event><Event ErrorLevel="0" Project="Jaavid" Source="Novin\frm_cheques.resx" Description="File successfully backed up as G:\Novin\Backup\Novin\frm_cheques.resx">
</Event><Event ErrorLevel="0" Project="Jaavid" Source="Novin\frm_experBalance.resx" Description="File successfully backed up as G:\Novin\Backup\Novin\frm_experBalance.resx">
</Event><Event ErrorLevel="0" Project="Jaavid" Source="Novin\frm_FATHER.resx" Description="File successfully backed up as G:\Novin\Backup\Novin\frm_FATHER.resx">
</Event><Event ErrorLevel="0" Project="Jaavid" Source="Novin\frm_findRecords.resx" Description="File successfully backed up as G:\Novin\Backup\Novin\frm_findRecords.resx">
</Event><Event ErrorLevel="0" Project="Jaavid" Source="Novin\frm_inputBox.resx" Description="File successfully backed up as G:\Novin\Backup\Novin\frm_inputBox.resx">
</Event><Event ErrorLevel="0" Project="Jaavid" Source="Novin\frm_invoiceExplorer.resx" Description="File successfully backed up as G:\Novin\Backup\Novin\frm_invoiceExplorer.resx">
</Event><Event ErrorLevel="0" Project="Jaavid" Source="Novin\frm_invoicesBuy.resx" Description="File successfully backed up as G:\Novin\Backup\Novin\frm_invoicesBuy.resx">
</Event><Event ErrorLevel="0" Project="Jaavid" Source="Novin\frm_invoicesSell.resx" Description="File successfully backed up as G:\Novin\Backup\Novin\frm_invoicesSell.resx">
</Event><Event ErrorLevel="0" Project="Jaavid" Source="Novin\frm_invoicesWasted.resx" Description="File successfully backed up as G:\Novin\Backup\Novin\frm_invoicesWasted.resx">
</Event><Event ErrorLevel="0" Project="Jaavid" Source="Novin\frm_issuseAccDoc.resx" Description="File successfully backed up as G:\Novin\Backup\Novin\frm_issuseAccDoc.resx">
</Event><Event ErrorLevel="0" Project="Jaavid" Source="Novin\frm_itemSelection.resx" Description="File successfully backed up as G:\Novin\Backup\Novin\frm_itemSelection.resx">
</Event><Event ErrorLevel="0" Project="Jaavid" Source="Novin\frm_master.resx" Description="File successfully backed up as G:\Novin\Backup\Novin\frm_master.resx">
</Event><Event ErrorLevel="0" Project="Jaavid" Source="Novin\frm_modify.resx" Description="File successfully backed up as G:\Novin\Backup\Novin\frm_modify.resx">
</Event><Event ErrorLevel="0" Project="Jaavid" Source="Novin\frm_msgBox.resx" Description="File successfully backed up as G:\Novin\Backup\Novin\frm_msgBox.resx">
</Event><Event ErrorLevel="0" Project="Jaavid" Source="Novin\frm_objectGrouping.resx" Description="File successfully backed up as G:\Novin\Backup\Novin\frm_objectGrouping.resx">
</Event><Event ErrorLevel="0" Project="Jaavid" Source="Novin\frm_objects.resx" Description="File successfully backed up as G:\Novin\Backup\Novin\frm_objects.resx">
</Event><Event ErrorLevel="0" Project="Jaavid" Source="Novin\frm_persons.resx" Description="File successfully backed up as G:\Novin\Backup\Novin\frm_persons.resx">
</Event><Event ErrorLevel="0" Project="Jaavid" Source="Novin\frm_primaryCycleEnd.resx" Description="File successfully backed up as G:\Novin\Backup\Novin\frm_primaryCycleEnd.resx">
</Event><Event ErrorLevel="0" Project="Jaavid" Source="Novin\frm_print.resx" Description="File successfully backed up as G:\Novin\Backup\Novin\frm_print.resx">
</Event><Event ErrorLevel="0" Project="Jaavid" Source="Novin\frm_reportPreview.resx" Description="File successfully backed up as G:\Novin\Backup\Novin\frm_reportPreview.resx">
</Event><Event ErrorLevel="0" Project="Jaavid" Source="Novin\frm_store.resx" Description="File successfully backed up as G:\Novin\Backup\Novin\frm_store.resx">
</Event><Event ErrorLevel="0" Project="Jaavid" Source="Novin\Properties\Resources.resx" Description="File successfully backed up as G:\Novin\Backup\Novin\Properties\Resources.resx">
</Event><Event ErrorLevel="0" Project="Jaavid" Source="Novin\rpt_balance.rpt" Description="File successfully backed up as G:\Novin\Backup\Novin\rpt_balance.rpt">
</Event><Event ErrorLevel="0" Project="Jaavid" Source="Novin\rpt_invoiceBuy.rpt" Description="File successfully backed up as G:\Novin\Backup\Novin\rpt_invoiceBuy.rpt">
</Event><Event ErrorLevel="0" Project="Jaavid" Source="Novin\rpt_invoiceSell.rpt" Description="File successfully backed up as G:\Novin\Backup\Novin\rpt_invoiceSell.rpt">
</Event><Event ErrorLevel="0" Project="Jaavid" Source="Novin\rpt_journal.rpt" Description="File successfully backed up as G:\Novin\Backup\Novin\rpt_journal.rpt">
</Event><Event ErrorLevel="0" Project="Jaavid" Source="Novin\rpt_ledger.rpt" Description="File successfully backed up as G:\Novin\Backup\Novin\rpt_ledger.rpt">
</Event><Event ErrorLevel="0" Project="Jaavid" Source="Novin\rpt_objectEntity.rpt" Description="File successfully backed up as G:\Novin\Backup\Novin\rpt_objectEntity.rpt">
</Event><Event ErrorLevel="0" Project="Jaavid" Source="Novin\rpt_objectWasted.rpt" Description="File successfully backed up as G:\Novin\Backup\Novin\rpt_objectWasted.rpt">
</Event><Event ErrorLevel="0" Project="Jaavid" Source="Novin\Jaavid.csproj" Description="Project converted successfully">
</Event><Event ErrorLevel="3" Project="Jaavid" Source="Novin\Jaavid.csproj" Description="Converted">
</Event><Event ErrorLevel="0" Project="reminder" Source="reminder\reminder.csproj" Description="Project file successfully backed up as G:\Novin\Backup\reminder\reminder.csproj">
</Event><Event ErrorLevel="0" Project="reminder" Source="reminder\frm_main.cs" Description="File successfully backed up as G:\Novin\Backup\reminder\frm_main.cs">
</Event><Event ErrorLevel="0" Project="reminder" Source="reminder\frm_main.Designer.cs" Description="File successfully backed up as G:\Novin\Backup\reminder\frm_main.Designer.cs">
</Event><Event ErrorLevel="0" Project="reminder" Source="reminder\Program.cs" Description="File successfully backed up as G:\Novin\Backup\reminder\Program.cs">
</Event><Event ErrorLevel="0" Project="reminder" Source="reminder\Properties\AssemblyInfo.cs" Description="File successfully backed up as G:\Novin\Backup\reminder\Properties\AssemblyInfo.cs">
</Event><Event ErrorLevel="0" Project="reminder" Source="reminder\Properties\Resources.Designer.cs" Description="File successfully backed up as G:\Novin\Backup\reminder\Properties\Resources.Designer.cs">
</Event><Event ErrorLevel="0" Project="reminder" Source="reminder\Properties\Settings.Designer.cs" Description="File successfully backed up as G:\Novin\Backup\reminder\Properties\Settings.Designer.cs">
</Event><Event ErrorLevel="0" Project="reminder" Source="reminder\Properties\Settings.settings" Description="File successfully backed up as G:\Novin\Backup\reminder\Properties\Settings.settings">
</Event><Event ErrorLevel="0" Project="reminder" Source="reminder\frm_main.resx" Description="File successfully backed up as G:\Novin\Backup\reminder\frm_main.resx">
</Event><Event ErrorLevel="0" Project="reminder" Source="reminder\Properties\Resources.resx" Description="File successfully backed up as G:\Novin\Backup\reminder\Properties\Resources.resx">
</Event><Event ErrorLevel="0" Project="reminder" Source="reminder\reminder.csproj" Description="Project converted successfully">
</Event><Event ErrorLevel="3" Project="reminder" Source="reminder\reminder.csproj" Description="Converted">
</Event><Event ErrorLevel="0" Project="jaavidTextbox" Source="jaavidTextbox\jaavidTextbox.csproj" Description="Project file successfully backed up as G:\Novin\Backup\jaavidTextbox\jaavidTextbox.csproj">
</Event><Event ErrorLevel="0" Project="jaavidTextbox" Source="jaavidTextbox\UserControl1.cs" Description="File successfully backed up as G:\Novin\Backup\jaavidTextbox\UserControl1.cs">
</Event><Event ErrorLevel="0" Project="jaavidTextbox" Source="jaavidTextbox\UserControl1.Designer.cs" Description="File successfully backed up as G:\Novin\Backup\jaavidTextbox\UserControl1.Designer.cs">
</Event><Event ErrorLevel="0" Project="jaavidTextbox" Source="jaavidTextbox\Properties\AssemblyInfo.cs" Description="File successfully backed up as G:\Novin\Backup\jaavidTextbox\Properties\AssemblyInfo.cs">
</Event><Event ErrorLevel="0" Project="jaavidTextbox" Source="jaavidTextbox\UserControl1.resx" Description="File successfully backed up as G:\Novin\Backup\jaavidTextbox\UserControl1.resx">
</Event><Event ErrorLevel="0" Project="jaavidTextbox" Source="jaavidTextbox\jaavidTextbox.csproj" Description="Project converted successfully">
</Event><Event ErrorLevel="3" Project="jaavidTextbox" Source="jaavidTextbox\jaavidTextbox.csproj" Description="Converted">
</Event><Event ErrorLevel="0" Project="setup.vdproj" Source="setup\setup.vdproj" Description="Project file successfully backed up as G:\Novin\Backup\setup\setup.vdproj">
</Event><Event ErrorLevel="0" Project="" Source="Novin.sln" Description="Solution converted successfully">
</Event><Event ErrorLevel="3" Project="" Source="Novin.sln" Description="Converted">
</Event><Event ErrorLevel="0" Project="Jaavid" Source="Novin\Jaavid.csproj" Description="Scan complete: Upgrade not required for project files.">
</Event><Event ErrorLevel="0" Project="reminder" Source="reminder\reminder.csproj" Description="Scan complete: Upgrade not required for project files.">
</Event><Event ErrorLevel="0" Project="jaavidTextbox" Source="jaavidTextbox\jaavidTextbox.csproj" Description="Scan complete: Upgrade not required for project files.">
</Event></UpgradeLog>